gym_wordle/__init__.py
gym_wordle/utils.py
gym_wordle/wordle.py
gym_wordle/dictionary/guess_list.csv
gym_wordle/dictionary/guess_list.npy
gym_wordle/dictionary/solution_list.csv
gym_wordle/dictionary/solution_list.npy
gym_wordle-0.1.3.dist-info/LICENSE
gym_wordle-0.1.3.dist-info/METADATA
gym_wordle-0.1.3.dist-info/WHEEL
gym_wordle-0.1.3.dist-info/top_level.txt
gym_wordle-0.1.3.dist-info/RECORD
