Metadata-Version: 2.1
Name: gym-wordle
Version: 0.1.3
Summary: OpenAI gym environment for training agents on Wordle
Home-page: https://github.com/DavidNKraemer/Gym-Wordle
Author: David Kraemer
Author-email: david.kraemer@stonybrook.edu
License: UNKNOWN
Platform: UNKNOWN
Classifier: Programming Language :: Python :: 3
Classifier: License :: OSI Approved :: MIT License
Classifier: Operating System :: OS Independent
Requires-Python: >=3.7
License-File: LICENSE
Requires-Dist: numpy (>=1.20)
Requires-Dist: gym (==0.19)
Requires-Dist: sty (==1.0)
